LICENSE.txt
MANIFEST.in
README.md
setup.py
jk_triologging/TrioBufferLogger.py
jk_triologging/TrioConsoleLogger.py
jk_triologging/TrioFileLogger.py
jk_triologging/TrioFilterLogger.py
jk_triologging/TrioLogWrapper.py
jk_triologging/TrioMulticastLogger.py
jk_triologging/TrioNamedMulticastLogger.py
jk_triologging/TrioNullLogger.py
jk_triologging/TrioStringListLogger.py
jk_triologging/__init__.py
jk_triologging/_inst.py
jk_triologging.egg-info/PKG-INFO
jk_triologging.egg-info/SOURCES.txt
jk_triologging.egg-info/dependency_links.txt
jk_triologging.egg-info/not-zip-safe
jk_triologging.egg-info/requires.txt
jk_triologging.egg-info/top_level.txt