Metadata-Version: 2.1
Name: jk-triologging
Version: 0.2019.10.4
Summary: This is a logging framework. It is based on jk_logging but can be used with Trio.
Home-page: https://github.com/jkpubsrc/python-module-jk-triologging
Author: Jürgen Knauth
Author-email: pubsrc@binary-overflow.de
License: Apache 2.0
Download-URL: https://github.com/jkpubsrc/python-module-jk-triologging/tarball/0.2019.10.4
Keywords: debugging,logging,trio
Platform: UNKNOWN
Classifier: Development Status :: 3 - Alpha
Classifier: Framework :: Trio
Classifier: License :: OSI Approved :: Apache Software License
Classifier: Topic :: Software Development :: Testing
Classifier: Topic :: System :: Logging
